pypotlib-0.0.13.data/headers/eigen3/signature_of_eigen3_matrix_library
pypotlib-0.0.13.data/headers/eigen3/unsupported/Eigen/MatrixFunctions
pypotlib-0.0.13.data/headers/eigen3/unsupported/Eigen/AdolcForward
pypotlib-0.0.13.data/headers/eigen3/unsupported/Eigen/AlignedVector3
pypotlib-0.0.13.data/headers/eigen3/unsupported/Eigen/OpenGLSupport
pypotlib-0.0.13.data/headers/eigen3/unsupported/Eigen/LevenbergMarquardt
pypotlib-0.0.13.data/headers/eigen3/unsupported/Eigen/AutoDiff
pypotlib-0.0.13.data/headers/eigen3/unsupported/Eigen/NumericalDiff
pypotlib-0.0.13.data/headers/eigen3/unsupported/Eigen/NonLinearOptimization
pypotlib-0.0.13.data/headers/eigen3/unsupported/Eigen/ArpackSupport
pypotlib-0.0.13.data/headers/eigen3/unsupported/Eigen/Skyline
pypotlib-0.0.13.data/headers/eigen3/unsupported/Eigen/BVH
pypotlib-0.0.13.data/headers/eigen3/unsupported/Eigen/SpecialFunctions
pypotlib-0.0.13.data/headers/eigen3/unsupported/Eigen/Splines
pypotlib-0.0.13.data/headers/eigen3/unsupported/Eigen/KroneckerProduct
pypotlib-0.0.13.data/headers/eigen3/unsupported/Eigen/IterativeSolvers
pypotlib-0.0.13.data/headers/eigen3/unsupported/Eigen/FFT
pypotlib-0.0.13.data/headers/eigen3/unsupported/Eigen/EulerAngles
pypotlib-0.0.13.data/headers/eigen3/unsupported/Eigen/SparseExtra
pypotlib-0.0.13.data/headers/eigen3/unsupported/Eigen/Polynomials
pypotlib-0.0.13.data/headers/eigen3/unsupported/Eigen/MoreVectorization
pypotlib-0.0.13.data/headers/eigen3/unsupported/Eigen/MPRealSupport
pypotlib-0.0.13.data/headers/eigen3/unsupported/Eigen/CXX11/ThreadPool
pypotlib-0.0.13.data/headers/eigen3/unsupported/Eigen/CXX11/TensorSymmetry
pypotlib-0.0.13.data/headers/eigen3/unsupported/Eigen/CXX11/Tensor
pypotlib-0.0.13.data/headers/eigen3/unsupported/Eigen/CXX11/src/util/MaxSizeVector.h
pypotlib-0.0.13.data/headers/eigen3/unsupported/Eigen/CXX11/src/util/CXX11Meta.h
pypotlib-0.0.13.data/headers/eigen3/unsupported/Eigen/CXX11/src/util/CXX11Workarounds.h
pypotlib-0.0.13.dist-info/RECORD
pypotlib-0.0.13.dist-info/WHEEL
pypotlib-0.0.13.dist-info/METADATA
