Metadata-Version: 2.1
Name: pypotlib
Version: 0.0.13
Summary: Python bindings and ASE adapters for potlib
Author-Email: Rohit Goswami <rog32@hi.is>
License: MIT
Project-URL: Source code, https://github.com/TheochemUI/pypotlib
Project-URL: Bug tracker, https://github.com/TheochemUI/pypotlib/issues
Requires-Python: >=3.8
Requires-Dist: numpy>=1.24.3
Requires-Dist: ase>=3.22.1
